kfsconfig/kfsconfig.py
kfsconfig-3.0.0.dist-info/METADATA
kfsconfig-3.0.0.dist-info/WHEEL
kfsconfig-3.0.0.dist-info/RECORD
